test_packaging_mnda/__init__.py
test_packaging_mnda/add.py
test_packaging_mnda-0.1.0.dist-info/METADATA
test_packaging_mnda-0.1.0.dist-info/WHEEL
test_packaging_mnda-0.1.0.dist-info/entry_points.txt
test_packaging_mnda-0.1.0.dist-info/RECORD
