Metadata-Version: 2.4
Name: test-packaging-mnda
Version: 0.1.0
Summary: Add your description here
Author-email: Reint Alberda van Ekenstein <reint.alberdavanekenstein@wur.nl>
Requires-Python: >=3.12
Requires-Dist: pytest>=8.3.5
Requires-Dist: ruff>=0.11.2
